{
    "id": "lesson-74",
    "title": "Energy Transfer",
    "questions": [
        {
            "id": 1,
            "text": "Which statement correctly describes how a coal-fired power plant converts energy into electricity?",
            "options": [
                {
                    "text": "The power plant creates new electrical energy from coal",
                    "isCorrect": 0,
                    "explanation": "Power plants don't create new energy. They convert existing energy from one form to another, following the law of conservation of energy."
                },
                {
                    "text": "The chemical energy in coal is converted to heat, which produces steam to spin turbines connected to generators, converting motion energy into electrical energy",
                    "isCorrect": 1,
                    "explanation": "This correctly describes the energy conversion process: chemical energy (coal) \u2192 heat energy \u2192 motion energy (steam turbines) \u2192 electrical energy."
                },
                {
                    "text": "The power plant generates unlimited electrical energy from a limited amount of coal",
                    "isCorrect": 0,
                    "explanation": "This violates the law of conservation of energy. The amount of electrical energy produced is limited by the amount of chemical energy stored in the coal."
                },
                {
                    "text": "The power plant directly converts coal into electrical energy without any intermediate steps",
                    "isCorrect": 0,
                    "explanation": "The conversion of coal to electricity involves multiple energy transformations and isn't direct. It requires intermediate steps involving heat and motion energy."
                }
            ],
            "funFact": "The largest coal-fired power plant in North America, the Robert W. Scherer Power Plant in Georgia, can convert enough chemical energy from coal to produce electricity for about 3.5 million homes!"
        },
        {
            "id": 2,
            "text": "Which statement correctly describes how plants use light energy from the sun for growth?",
            "options": [
                {
                    "text": "Plants store light energy directly in their leaves without converting it to other forms",
                    "isCorrect": 0,
                    "explanation": "Plants don't store light energy directly - they must first convert it to chemical energy through photosynthesis"
                },
                {
                    "text": "Plants absorb heat energy from sunlight to melt nutrients in the soil",
                    "isCorrect": 0,
                    "explanation": "While plants do receive heat from the sun, they don't use it to melt nutrients. They use light energy in photosynthesis to make their own food"
                },
                {
                    "text": "Plants convert light energy into chemical energy they can use to grow and produce food",
                    "isCorrect": 1,
                    "explanation": "Plants capture sunlight and through photosynthesis convert it into chemical energy stored in food, which they use for growth and other life processes"
                },
                {
                    "text": "Plants reflect light energy back into space which helps them grow taller",
                    "isCorrect": 0,
                    "explanation": "Plants actually absorb light energy rather than reflect it. Reflecting light would not provide them with the energy they need for growth"
                }
            ],
            "funFact": "Some plants can detect and grow towards light sources through a process called phototropism. This allows them to maximize their exposure to sunlight and optimize their energy capture for growth!"
        },
        {
            "id": 3,
            "text": "Which of the following best describes what energy is?",
            "options": [
                {
                    "text": "The ability to do work or make things happen",
                    "isCorrect": 1,
                    "explanation": "This is correct! Energy is defined as the ability to do work, which means it can make things happen - from powering your video games to helping you ride a bike."
                },
                {
                    "text": "A type of force that only moves objects",
                    "isCorrect": 0,
                    "explanation": "This is incorrect. While energy can cause motion, it does much more than just move objects. Energy can also produce light, sound, and heat."
                },
                {
                    "text": "Something that can only be created by machines",
                    "isCorrect": 0,
                    "explanation": "This is incorrect. Energy is not just created by machines - it exists in many forms in nature, like sunlight, and can be converted from one form to another."
                },
                {
                    "text": "Electricity stored in batteries",
                    "isCorrect": 0,
                    "explanation": "This is incorrect. While batteries do store energy, this is just one form of energy. Energy exists in many forms like light, sound, heat, and motion."
                }
            ],
            "funFact": "Did you know that the energy you get from eating one chocolate chip cookie could charge a smartphone for about 10 minutes? Our bodies are incredibly efficient at converting the chemical energy in food into other forms of energy we need!"
        },
        {
            "id": 4,
            "text": "A drummer is playing their drum set at a concert. How does the sound reach the audience members in the back of the venue?",
            "options": [
                {
                    "text": "The sound waves travel through the air from the drum to the listeners' ears",
                    "isCorrect": 1,
                    "explanation": "Sound energy transfers through waves that travel through the air from the source (drum) to the receiver (ears)"
                },
                {
                    "text": "The drum shoots tiny particles that hit the listeners' ears",
                    "isCorrect": 0,
                    "explanation": "Sound does not transfer through particles being shot - it transfers through waves in the air"
                },
                {
                    "text": "The drum creates light that carries the sound to listeners",
                    "isCorrect": 0,
                    "explanation": "Sound transfers through sound waves in the air, not through light waves"
                },
                {
                    "text": "The sound teleports instantly from the drum to the listeners",
                    "isCorrect": 0,
                    "explanation": "Sound takes time to travel through the air - it does not teleport or transfer instantly"
                }
            ],
            "funFact": "The speed of sound in air is about 343 meters per second (767 mph) at room temperature. This means that at a large concert venue that's 100 meters long, it takes about 0.3 seconds for the sound to reach people in the back!"
        },
        {
            "id": 5,
            "text": "When someone pedals a bicycle connected to a generator to power a light bulb, what is the sequence of energy conversions that takes place?",
            "options": [
                {
                    "text": "Motion energy \u2192 Electrical energy \u2192 Light energy",
                    "isCorrect": 1,
                    "explanation": "This is correct! The motion of pedaling creates motion energy, which the generator converts to electrical energy, and finally the light bulb converts electrical energy into light energy."
                },
                {
                    "text": "Chemical energy \u2192 Motion energy \u2192 Light energy",
                    "isCorrect": 0,
                    "explanation": "While chemical energy from food does help the person pedal, this sequence misses the crucial electrical energy step that happens in the generator."
                },
                {
                    "text": "Electrical energy \u2192 Motion energy \u2192 Light energy",
                    "isCorrect": 0,
                    "explanation": "This sequence is incorrect because electrical energy comes from converting the motion energy, not the other way around."
                },
                {
                    "text": "Motion energy \u2192 Light energy \u2192 Electrical energy",
                    "isCorrect": 0,
                    "explanation": "This sequence is out of order. The generator must first convert motion to electrical energy before it can be converted to light."
                }
            ],
            "funFact": "The world's first bicycle-powered generator was created in the late 1800s. Today, some gyms use exercise bikes connected to generators to help power their facilities, turning workout energy into useful electricity!"
        },
        {
            "id": 6,
            "text": "A science class is designing a bicycle-powered generator for their school's science fair. They need to convert the motion energy from pedaling into electrical energy to power small devices. The students have four different design proposals. Which design would be the safest and most cost-effective way to convert motion energy into electrical energy?",
            "options": [
                {
                    "text": "Create friction between the wheel and a metal plate to generate electricity",
                    "isCorrect": 0,
                    "explanation": "This design would waste energy as heat through friction and could be dangerous. It's not an efficient or safe way to generate electrical energy."
                },
                {
                    "text": "Connect the bicycle wheel to a generator that transforms the spinning motion into electrical energy",
                    "isCorrect": 1,
                    "explanation": "This is the most effective and safe design. The generator properly converts mechanical energy from the wheel's motion into electrical energy that can power devices."
                },
                {
                    "text": "Use multiple batteries connected to the wheel to store motion energy",
                    "isCorrect": 0,
                    "explanation": "Batteries store electrical energy but cannot directly convert motion energy. This design wouldn't work as batteries can't transform motion into electricity."
                },
                {
                    "text": "Attach the bicycle wheel directly to copper wires that connect to the devices",
                    "isCorrect": 0,
                    "explanation": "This design is unsafe as direct contact between the wheel and wires could cause damage and wouldn't effectively convert motion energy to electrical energy."
                }
            ],
            "funFact": "The first bicycle-powered generators were used in the early 1900s for powering early radio sets and lighting systems in rural areas before widespread electricity was available. Today, some gyms use exercise bikes connected to generators to help power their facilities!"
        },
        {
            "id": 7,
            "text": "A student is experimenting with a bicycle generator setup to power different devices. The setup includes a bicycle connected to a generator, which can power a light bulb and charge a phone. When the student pedals the bicycle, which sequence of energy transformations occurs to light up the bulb?",
            "options": [
                {
                    "text": "Motion energy \u2192 Electrical energy \u2192 Light energy",
                    "isCorrect": 1,
                    "explanation": "This is correct! When pedaling, your motion energy turns the generator, which converts it to electrical energy. The electrical energy then flows through wires to the light bulb, where it's converted to light energy."
                },
                {
                    "text": "Electrical energy \u2192 Motion energy \u2192 Light energy",
                    "isCorrect": 0,
                    "explanation": "This sequence is incorrect. The energy transformation begins with motion (pedaling), not electrical energy. The generator converts motion to electrical energy, not the other way around."
                },
                {
                    "text": "Motion energy \u2192 Light energy \u2192 Electrical energy",
                    "isCorrect": 0,
                    "explanation": "This sequence is out of order. The generator must first convert motion energy to electrical energy before it can be converted to light energy in the bulb."
                },
                {
                    "text": "Chemical energy \u2192 Motion energy \u2192 Light energy",
                    "isCorrect": 0,
                    "explanation": "While chemical energy from your muscles helps you pedal, this sequence misses the crucial electrical energy stage that occurs when the generator converts motion energy to electrical energy."
                }
            ],
            "funFact": "The same principle used in bicycle generators is used in many hydroelectric dams, where falling water (motion energy) spins turbines connected to generators, producing enough electrical energy to power thousands of homes!"
        },
        {
            "id": 8,
            "text": "A string of holiday lights is plugged into an electrical outlet. When the lights are turned on, they feel warm to the touch. This warmth indicates that not all electrical energy is being converted to light. What is happening to the 'lost' electrical energy in this system?",
            "options": [
                {
                    "text": "The electrical energy is being converted to heat energy",
                    "isCorrect": 1,
                    "explanation": "When electrical energy flows through the light bulbs, some energy is converted to heat due to resistance in the wires and bulbs. This is an example of energy transfer, not energy loss."
                },
                {
                    "text": "The electrical energy is stored in the light bulbs",
                    "isCorrect": 0,
                    "explanation": "Light bulbs do not store energy - they convert electrical energy into light and heat energy immediately as electricity flows through them."
                },
                {
                    "text": "The electrical energy returns to the power outlet",
                    "isCorrect": 0,
                    "explanation": "Once electrical energy enters the circuit, it doesn't return to the outlet unchanged. It is converted to other forms of energy like light and heat."
                },
                {
                    "text": "The electrical energy disappears completely",
                    "isCorrect": 0,
                    "explanation": "Energy cannot disappear or be destroyed. It always converts from one form to another according to the law of conservation of energy."
                }
            ],
            "funFact": "Modern LED holiday lights are much more efficient than traditional incandescent bulbs, converting about 90% of electrical energy to light and only 10% to heat. In contrast, old-style incandescent bulbs convert about 90% of electrical energy to heat and only 10% to light!"
        },
        {
            "id": 9,
            "text": "A student is experimenting with a simple circuit containing a battery, wires, and a buzzer. What would happen to the sound from the buzzer if the student replaces the battery with one that has twice the voltage?",
            "options": [
                {
                    "text": "The buzzer will produce a softer sound because the extra voltage reduces energy conversion",
                    "isCorrect": 0,
                    "explanation": "This is incorrect - more voltage means more electrical energy is available for conversion to sound energy, not less"
                },
                {
                    "text": "The buzzer will stop working because too much voltage will break it",
                    "isCorrect": 0,
                    "explanation": "While extremely high voltages could damage a buzzer, simply doubling the voltage within the device's operating range will just result in louder sound"
                },
                {
                    "text": "The sound will remain exactly the same because voltage doesn't affect sound production",
                    "isCorrect": 0,
                    "explanation": "The amount of electrical energy available does affect the sound production - more voltage means more energy for conversion to sound"
                },
                {
                    "text": "The buzzer will produce a louder sound because more electrical energy is being converted to sound energy",
                    "isCorrect": 1,
                    "explanation": "A higher voltage battery provides more electrical energy, which leads to stronger vibrations in the buzzer and therefore a louder sound"
                }
            ],
            "funFact": "Many musical instruments actually use electrical energy conversion similar to buzzers! Electric guitars convert string vibrations to electrical signals, which are then converted back to amplified sound through speakers."
        },
        {
            "id": 10,
            "text": "A science class is designing passive solar heaters for keeping food warm during outdoor events. They have access to different materials to test. Which material would be most effective for converting sunlight into heat energy in their solar heater design?",
            "options": [
                {
                    "text": "Black metal sheet",
                    "isCorrect": 1,
                    "explanation": "Black metal is excellent at absorbing light energy and converting it to heat energy. It also conducts heat well, making it very effective for solar heating."
                },
                {
                    "text": "Shiny aluminum foil",
                    "isCorrect": 0,
                    "explanation": "Shiny aluminum foil reflects most light energy rather than absorbing it, making it poor at converting light to heat energy."
                },
                {
                    "text": "Clear glass panel",
                    "isCorrect": 0,
                    "explanation": "While clear glass allows light to pass through, it doesn't effectively convert light energy to heat energy since most light passes through rather than being absorbed."
                },
                {
                    "text": "White plastic sheet",
                    "isCorrect": 0,
                    "explanation": "White surfaces reflect most light energy rather than absorbing it, making white plastic inefficient at converting light energy to heat energy."
                }
            ],
            "funFact": "The world's largest solar thermal power plant, located in the Mojave Desert, uses over 300,000 mirrors to concentrate sunlight onto black-coated tubes containing water, converting light energy into heat energy to generate electricity!"
        },
        {
            "id": 11,
            "text": "A solar-powered calculator is being used in different locations throughout the day. In which situation would the energy conversion from light to electrical energy be most efficient?",
            "options": [
                {
                    "text": "Using the calculator at sunset",
                    "isCorrect": 0,
                    "explanation": "The low angle and reduced intensity of sunlight at sunset provides less light energy for conversion, reducing the efficiency of the solar cell."
                },
                {
                    "text": "Using the calculator inside a dimly lit room",
                    "isCorrect": 0,
                    "explanation": "Low light conditions reduce the amount of light energy available for conversion to electrical energy, making the solar cell less efficient."
                },
                {
                    "text": "Using the calculator in direct sunlight on a clear day",
                    "isCorrect": 1,
                    "explanation": "Direct sunlight provides maximum light energy for the solar cell to convert to electrical energy, allowing for the most efficient energy conversion."
                },
                {
                    "text": "Using the calculator on a cloudy afternoon",
                    "isCorrect": 0,
                    "explanation": "Cloud cover reduces the amount of light reaching the solar cell, resulting in less efficient energy conversion."
                }
            ],
            "funFact": "The first solar-powered calculator was invented in 1978 by Sharp Corporation. Modern solar calculators can work for several days even after brief exposure to light because they combine solar cells with rechargeable batteries to store excess energy!"
        },
        {
            "id": 12,
            "text": "In a solar-powered toy car system, energy undergoes multiple conversions: sunlight \u2192 electrical energy (via solar cell) \u2192 motion (via motor). Where in this system would energy loss most likely occur, and what could be done to minimize it?",
            "options": [
                {
                    "text": "At the solar cell, and painting it black would increase energy conversion",
                    "isCorrect": 0,
                    "explanation": "While solar cells do have some energy loss, painting them black would actually reduce their efficiency. Solar cells are designed with specific materials to optimize photon absorption."
                },
                {
                    "text": "At the toy car's wheels, and using larger wheels would eliminate all energy loss",
                    "isCorrect": 0,
                    "explanation": "While larger wheels might reduce some friction with the ground, they cannot eliminate all energy loss. Energy is still lost through friction between the wheels and the surface, as well as air resistance."
                },
                {
                    "text": "At the motor-to-motion conversion, and adding lubricant to moving parts would help reduce friction losses",
                    "isCorrect": 1,
                    "explanation": "Motors convert electrical energy to motion, but friction between moving parts causes energy loss as heat. Proper lubrication reduces this friction, maximizing the energy available for motion."
                },
                {
                    "text": "In the wires, and making them thicker would eliminate all energy loss",
                    "isCorrect": 0,
                    "explanation": "While thicker wires can reduce energy loss due to resistance, they cannot eliminate all energy loss. Some electrical energy will always be converted to heat in the wires."
                }
            ],
            "funFact": "The most efficient electric motors today can convert up to 97% of electrical energy into mechanical energy, but early electric motors in the 1800s were only about 50% efficient. This improvement is mainly due to better materials and designs that reduce energy losses from friction and heat."
        },
        {
            "id": 13,
            "text": "In a simple electronic setup, there are three devices connected to a battery: a light bulb, a speaker, and a small motor. How is the electrical energy from the battery transformed differently in each device?",
            "options": [
                {
                    "text": "All three devices convert electrical energy into heat energy only",
                    "isCorrect": 0,
                    "explanation": "While some heat is produced as a byproduct, each device primarily converts electrical energy into a different form of energy for its main function"
                },
                {
                    "text": "All three devices convert electrical energy into motion energy",
                    "isCorrect": 0,
                    "explanation": "Only the motor is designed to convert electrical energy primarily into motion energy. The light bulb and speaker convert energy into light and sound respectively"
                },
                {
                    "text": "The light bulb converts electrical energy to light energy, the speaker converts it to sound energy, and the motor converts it to motion energy",
                    "isCorrect": 1,
                    "explanation": "Each device transforms electrical energy into a different form - the light bulb produces light, the speaker creates sound waves, and the motor generates mechanical motion"
                },
                {
                    "text": "The light bulb and speaker both produce sound energy, while the motor produces motion energy",
                    "isCorrect": 0,
                    "explanation": "The light bulb produces light energy, not sound energy. Only the speaker is designed to produce sound energy"
                }
            ],
            "funFact": "While these devices convert electrical energy into their primary forms (light, sound, or motion), they all produce some heat as a byproduct. This is why electronic devices feel warm after being used for a while!"
        },
        {
            "id": 14,
            "text": "In a science demonstration, a drummer plays a bass drum next to a bowl of water. As the drum is played, ripples appear on the water's surface. What best explains how energy is being transferred from the drum to create these ripples?",
            "options": [
                {
                    "text": "Light from the drum reflects off the water surface causing the ripples to form",
                    "isCorrect": 0,
                    "explanation": "Light reflection does not cause water ripples. The ripples are caused by sound energy transfer, not light energy."
                },
                {
                    "text": "Sound waves from the drum travel through the air and transfer energy to the water molecules, causing them to move up and down",
                    "isCorrect": 1,
                    "explanation": "Sound travels as waves through air by transferring energy from molecule to molecule. When these waves reach the water, they transfer their energy to the water molecules, creating visible ripples."
                },
                {
                    "text": "Heat from the drum warms the air which then creates the ripples in the water",
                    "isCorrect": 0,
                    "explanation": "While drums can produce some heat, the ripples are not caused by heat transfer. They are created by sound wave energy moving through the air."
                },
                {
                    "text": "The drum creates wind that blows across the water surface making ripples",
                    "isCorrect": 0,
                    "explanation": "The drum's vibrations create sound waves, not wind. The ripples are formed by sound energy transfer through the air, not by moving air (wind)."
                }
            ],
            "funFact": "Some aquatic animals like whales use sound waves underwater to communicate over vast distances - up to hundreds of miles! The sound waves travel much faster and farther in water than in air because water molecules are packed more closely together."
        },
        {
            "id": 15,
            "text": "When a bicycle is used to power a small fan, which sequence correctly shows how energy is transferred from the cyclist to the fan blades?",
            "options": [
                {
                    "text": "Electrical energy \u2192 Motion energy \u2192 Generator \u2192 Fan motor \u2192 Motion energy",
                    "isCorrect": 0,
                    "explanation": "This sequence is incorrect because it starts with electrical energy. The energy transfer begins with the motion energy from pedaling."
                },
                {
                    "text": "Motion energy \u2192 Fan motor \u2192 Electrical energy \u2192 Generator \u2192 Motion energy",
                    "isCorrect": 0,
                    "explanation": "This sequence is incorrect because it places the fan motor before the generator. The generator must first convert motion energy to electrical energy."
                },
                {
                    "text": "Motion energy \u2192 Electrical energy \u2192 Generator \u2192 Motion energy \u2192 Fan motor",
                    "isCorrect": 0,
                    "explanation": "This sequence is incorrect because it shows electrical energy before the generator. The generator is what converts motion energy into electrical energy."
                },
                {
                    "text": "Motion energy \u2192 Generator \u2192 Electrical energy \u2192 Fan motor \u2192 Motion energy",
                    "isCorrect": 1,
                    "explanation": "This is the correct sequence. The cyclist's pedaling creates motion energy, which the generator converts to electrical energy. The fan motor then converts this electrical energy back into motion energy to spin the blades."
                }
            ],
            "funFact": "The first bicycle-powered generator was invented in the late 1800s. Today, some gyms use exercise bikes connected to generators to help power their facilities, turning human workout energy into usable electricity!"
        }
    ]
}